icemedia/__init__.py
icemedia/iceflow.py
icemedia/iceflow_server.py
icemedia/jack_tools.py
icemedia/jsonrpyc.py
icemedia/py.typed
icemedia/python_mpv_jsonipc.py
icemedia/sound_player.py
icemedia-0.2.0.dist-info/WHEEL
icemedia-0.2.0.dist-info/METADATA
icemedia-0.2.0.dist-info/RECORD
