Metadata-Version: 2.4
Name: icemedia
Version: 0.2.0
Summary: Media handling library with GStreamer wrapper, sound player, and Jack manager
Author: Daniel Dunn
License-Expression: LGPL-2.0-or-later
Requires-Dist: jack-client>=0.5.4
Requires-Dist: scullery>=0.2.0
Requires-Python: >=3.11
